s3headerize/__init__.py
s3headerize/__main__.py
s3headerize/bucket_headerizer.py
s3headerize/object_headerizer.py
s3headerize/test_bucket_headerizer.py
s3headerize/test_object_headerizer.py
s3headerize-1.0.dist-info/LICENSE
s3headerize-1.0.dist-info/METADATA
s3headerize-1.0.dist-info/WHEEL
s3headerize-1.0.dist-info/top_level.txt
s3headerize-1.0.dist-info/RECORD
