Metadata-Version: 2.1
Name: s3headerize
Version: 1.0
Summary: A Python package for setting HTTP headers on Amazon Web Services (AWS) S3 objects.
Home-page: https://github.com/cariad/py-s3headerize
Author: Cariad Eccleston
Author-email: cariad@cariad.me
License: MIT
Platform: UNKNOWN
Classifier: Development Status :: 5 - Production/Stable
Classifier: Environment :: Console
Classifier: Intended Audience :: Developers
Classifier: License :: OSI Approved :: MIT License
Classifier: Natural Language :: English
Classifier: Programming Language :: Python :: 3
Classifier: Operating System :: OS Independent
Classifier: Topic :: Internet :: WWW/HTTP :: Site Management
Requires-Dist: boto3
Requires-Dist: pyyaml
Provides-Extra: dev
Requires-Dist: autopep8 ; extra == 'dev'
Requires-Dist: coverage ; extra == 'dev'
Requires-Dist: mock ; extra == 'dev'
Requires-Dist: pylint ; extra == 'dev'
